webnyx/__init__.py
webnyx/app.py
webnyx/middleware.py
webnyx-0.1.1.dist-info/METADATA
webnyx-0.1.1.dist-info/WHEEL
webnyx-0.1.1.dist-info/top_level.txt
webnyx-0.1.1.dist-info/RECORD
