Metadata-Version: 2.1
Name: webnyx
Version: 0.1.1
Summary: Simple Python Web Framework. It was built for learning purposes.
Home-page: https://github.com/sobirjonovme/WebNyx
Author: Asadbek Sobirjonov
Author-email: muhandis.asadbek@gmail.com
License: MIT
Platform: UNKNOWN
Classifier: License :: OSI Approved :: MIT License
Classifier: Programming Language :: Python
Classifier: Programming Language :: Python :: 3
Classifier: Programming Language :: Python :: 3.6
Classifier: Programming Language :: Python :: Implementation :: CPython
Classifier: Programming Language :: Python :: Implementation :: PyPy
Requires-Python: >=3.9.0
Requires-Dist: Jinja2 ==3.1.4
Requires-Dist: parse ==1.20.2
Requires-Dist: pytest-cov ==5.0.0
Requires-Dist: pytest ==8.2.2
Requires-Dist: requests-wsgi-adapter ==0.4.1
Requires-Dist: requests ==2.32.3
Requires-Dist: webob ==1.8.7
Requires-Dist: whitenoise ==6.7.0
